ipify/__init__.py
ipify/exceptions.py
ipify/ipify.py
ipify/settings.py
ipify-1.0.0.dist-info/DESCRIPTION.rst
ipify-1.0.0.dist-info/METADATA
ipify-1.0.0.dist-info/metadata.json
ipify-1.0.0.dist-info/RECORD
ipify-1.0.0.dist-info/top_level.txt
ipify-1.0.0.dist-info/WHEEL
